glarki_bmi_calculator/__init__.py
glarki_bmi_calculator/main.py
glarki_bmi_calculator-0.3.3.dist-info/METADATA
glarki_bmi_calculator-0.3.3.dist-info/WHEEL
glarki_bmi_calculator-0.3.3.dist-info/entry_points.txt
glarki_bmi_calculator-0.3.3.dist-info/top_level.txt
glarki_bmi_calculator-0.3.3.dist-info/RECORD
