Metadata-Version: 2.1
Name: glarki_bmi_calculator
Version: 0.3.3
Summary: Calculate Body-Mass Index
Author: Gijs Luijten
